xmlrpccomp/__init__.py
xmlrpccomp-1.0.0.dist-info/METADATA
xmlrpccomp-1.0.0.dist-info/RECORD
xmlrpccomp-1.0.0.dist-info/WHEEL
xmlrpccomp-1.0.0.dist-info/top_level.txt
