Metadata-Version: 2.1
Name: xmlrpccomp
Version: 1.0.0
Summary: xmlrpc comp (python2 and 3)
Home-page: https://github.com/bjtj/xmlrpccomp
Author: tj
Author-email: bjtj10@gmail.com
License: UNKNOWN
Platform: UNKNOWN
Classifier: Programming Language :: Python :: 3
Classifier: License :: OSI Approved :: MIT License
Classifier: Operating System :: OS Independent
